api_query
